{
    "ClassName": "",
    "Include": "",
    "Chance": 1.0,
    "Quantity": {
        "Min": 0.0,
        "Max": 0.0
    },
    "Health": [],
    "InventoryAttachments": [
        {
            "SlotName": "Hips",
            "Items": [
                {
                    "ClassName": "FOG_MRB_Belt_CB",
                    "Include": "",
                    "Chance": 1.0,
                    "Quantity": {
                        "Min": 0.0,
                        "Max": 0.0
                    },
                    "Health": [],
                    "InventoryAttachments": [
                        {
                            "SlotName": "gloves",
                            "Items": [
                                {
                                    "ClassName": "WorkingGloves_Black",
                                    "Include": "",
                                    "Chance": 1.0,
                                    "Quantity": {
                                        "Min": 0.0,
                                        "Max": 0.0
                                    },
                                    "Health": [],
                                    "InventoryAttachments": [],
                                    "InventoryCargo": [],
                                    "ConstructionPartsBuilt": [],
                                    "Sets": []
                                }
                            ]
                        },
                        {
                            "SlotName": "FOG_FannyPack",
                            "Items": [
                                {
                                    "ClassName": "FOG_Pouch_FannyPack_Black",
                                    "Include": "",
                                    "Chance": 1.0,
                                    "Quantity": {
                                        "Min": 0.0,
                                        "Max": 0.0
                                    },
                                    "Health": [],
                                    "InventoryAttachments": [],
                                    "InventoryCargo": [
                                        {
                                            "ClassName": "FreezeBar_gold",
                                            "Include": "",
                                            "Chance": 0.1,
                                            "Quantity": {
                                                "Min": 0.0,
                                                "Max": 1.0
                                            },
                                            "Health": [],
                                            "InventoryAttachments": [],
                                            "InventoryCargo": [],
                                            "ConstructionPartsBuilt": [],
                                            "Sets": []
                                        },
                                        {
                                            "ClassName": "QPK_GreenBat",
                                            "Include": "",
                                            "Chance": 0.1,
                                            "Quantity": {
                                                "Min": 0.0,
                                                "Max": 1.0
                                            },
                                            "Health": [],
                                            "InventoryAttachments": [],
                                            "InventoryCargo": [],
                                            "ConstructionPartsBuilt": [],
                                            "Sets": []
                                        },
                                        {
                                            "ClassName": "QPK_Egg",
                                            "Include": "",
                                            "Chance": 0.1,
                                            "Quantity": {
                                                "Min": 0.0,
                                                "Max": 1.0
                                            },
                                            "Health": [],
                                            "InventoryAttachments": [],
                                            "InventoryCargo": [],
                                            "ConstructionPartsBuilt": [],
                                            "Sets": []
                                        },
                                        {
                                            "ClassName": "QPK_Chiken",
                                            "Include": "",
                                            "Chance": 0.1,
                                            "Quantity": {
                                                "Min": 0.0,
                                                "Max": 1.0
                                            },
                                            "Health": [],
                                            "InventoryAttachments": [],
                                            "InventoryCargo": [],
                                            "ConstructionPartsBuilt": [],
                                            "Sets": []
                                        }
                                    ],
                                    "ConstructionPartsBuilt": [],
                                    "Sets": []
                                }
                            ]
                        },
                        {
                            "SlotName": "FOG_MRB_singlemag",
                            "Items": [
                                {
                                    "ClassName": "FOG_TV110T_FastMag_Tan",
                                    "Include": "",
                                    "Chance": 1.0,
                                    "Quantity": {
                                        "Min": 0.0,
                                        "Max": 0.0
                                    },
                                    "Health": [],
                                    "InventoryAttachments": [],
                                    "InventoryCargo": [],
                                    "ConstructionPartsBuilt": [],
                                    "Sets": []
                                }
                            ]
                        },
                        {
                            "SlotName": "FOG_Ronin_Holsterslot",
                            "Items": [
                                {
                                    "ClassName": "FOG_RTGFB_Holster_Tan",
                                    "Include": "",
                                    "Chance": 1.0,
                                    "Quantity": {
                                        "Min": 0.0,
                                        "Max": 0.0
                                    },
                                    "Health": [],
                                    "InventoryAttachments": [
                                        {
                                            "SlotName": "Pistol",
                                            "Items": [
                                                {
                                                    "ClassName": "BO_FiveSeven",
                                                    "Include": "",
                                                    "Chance": 1.0,
                                                    "Quantity": {
                                                        "Min": 0.0,
                                                        "Max": 0.0
                                                    },
                                                    "Health": [],
                                                    "InventoryAttachments": [
                                                        {
                                                            "SlotName": "Magazine",
                                                            "Items": [
                                                                {
                                                                    "ClassName": "BO_Mag_FiveSeven_20rnd",
                                                                    "Include": "",
                                                                    "Chance": 1.0,
                                                                    "Quantity": {
                                                                        "Min": 1.0,
                                                                        "Max": 1.0
                                                                    },
                                                                    "Health": [],
                                                                    "InventoryAttachments": [],
                                                                    "InventoryCargo": [],
                                                                    "ConstructionPartsBuilt": [],
                                                                    "Sets": []
                                                                }
                                                            ]
                                                        }
                                                    ],
                                                    "InventoryCargo": [],
                                                    "ConstructionPartsBuilt": [],
                                                    "Sets": []
                                                }
                                            ]
                                        }
                                    ],
                                    "InventoryCargo": [],
                                    "ConstructionPartsBuilt": [],
                                    "Sets": []
                                }
                            ]
                        },
                        {
                            "SlotName": "FOG_LBT_pouch",
                            "Items": [
                                {
                                    "ClassName": "FOG_Pouch_LBT_CB",
                                    "Include": "",
                                    "Chance": 1.0,
                                    "Quantity": {
                                        "Min": 0.0,
                                        "Max": 0.0
                                    },
                                    "Health": [],
                                    "InventoryAttachments": [
                                        {
                                            "SlotName": "MedicalBandage",
                                            "Items": [
                                                {
                                                    "ClassName": "BandageDressing",
                                                    "Include": "",
                                                    "Chance": 1.0,
                                                    "Quantity": {
                                                        "Min": 1.0,
                                                        "Max": 1.0
                                                    },
                                                    "Health": [],
                                                    "InventoryAttachments": [],
                                                    "InventoryCargo": [],
                                                    "ConstructionPartsBuilt": [],
                                                    "Sets": []
                                                }
                                            ]
                                        },
                                        {
                                            "SlotName": "FOG_painkillers2",
                                            "Items": [
                                                {
                                                    "ClassName": "PainkillerTablets",
                                                    "Include": "",
                                                    "Chance": 1.0,
                                                    "Quantity": {
                                                        "Min": 1.0,
                                                        "Max": 1.0
                                                    },
                                                    "Health": [],
                                                    "InventoryAttachments": [],
                                                    "InventoryCargo": [],
                                                    "ConstructionPartsBuilt": [],
                                                    "Sets": []
                                                }
                                            ]
                                        },
                                        {
                                            "SlotName": "FOG_VitaminBottle",
                                            "Items": [
                                                {
                                                    "ClassName": "VitaminBottle",
                                                    "Include": "",
                                                    "Chance": 1.0,
                                                    "Quantity": {
                                                        "Min": 1.0,
                                                        "Max": 1.0
                                                    },
                                                    "Health": [],
                                                    "InventoryAttachments": [],
                                                    "InventoryCargo": [],
                                                    "ConstructionPartsBuilt": [],
                                                    "Sets": []
                                                }
                                            ]
                                        },
                                        {
                                            "SlotName": "FOG_tetracycline",
                                            "Items": [
                                                {
                                                    "ClassName": "TetracyclineAntibiotics",
                                                    "Include": "",
                                                    "Chance": 1.0,
                                                    "Quantity": {
                                                        "Min": 1.0,
                                                        "Max": 1.0
                                                    },
                                                    "Health": [],
                                                    "InventoryAttachments": [],
                                                    "InventoryCargo": [],
                                                    "ConstructionPartsBuilt": [],
                                                    "Sets": []
                                                }
                                            ]
                                        },
                                        {
                                            "SlotName": "FOG_EpinephrineA",
                                            "Items": [
                                                {
                                                    "ClassName": "Epinephrine",
                                                    "Include": "",
                                                    "Chance": 1.0,
                                                    "Quantity": {
                                                        "Min": 0.0,
                                                        "Max": 0.0
                                                    },
                                                    "Health": [],
                                                    "InventoryAttachments": [],
                                                    "InventoryCargo": [],
                                                    "ConstructionPartsBuilt": [],
                                                    "Sets": []
                                                }
                                            ]
                                        },
                                        {
                                            "SlotName": "FOG_Morphine",
                                            "Items": [
                                                {
                                                    "ClassName": "Morphine",
                                                    "Include": "",
                                                    "Chance": 1.0,
                                                    "Quantity": {
                                                        "Min": 0.0,
                                                        "Max": 0.0
                                                    },
                                                    "Health": [],
                                                    "InventoryAttachments": [],
                                                    "InventoryCargo": [],
                                                    "ConstructionPartsBuilt": [],
                                                    "Sets": []
                                                }
                                            ]
                                        },
                                        {
                                            "SlotName": "FOG_EpinephrineB",
                                            "Items": [
                                                {
                                                    "ClassName": "AntiChemInjector",
                                                    "Include": "",
                                                    "Chance": 1.0,
                                                    "Quantity": {
                                                        "Min": 0.0,
                                                        "Max": 0.0
                                                    },
                                                    "Health": [],
                                                    "InventoryAttachments": [],
                                                    "InventoryCargo": [],
                                                    "ConstructionPartsBuilt": [],
                                                    "Sets": []
                                                }
                                            ]
                                        },
                                        {
                                            "SlotName": "FOG_TransfusionKit",
                                            "Items": [
                                                {
                                                    "ClassName": "SalineBagIV",
                                                    "Include": "",
                                                    "Chance": 1.0,
                                                    "Quantity": {
                                                        "Min": 0.0,
                                                        "Max": 0.0
                                                    },
                                                    "Health": [],
                                                    "InventoryAttachments": [],
                                                    "InventoryCargo": [],
                                                    "ConstructionPartsBuilt": [],
                                                    "Sets": []
                                                }
                                            ]
                                        },
                                        {
                                            "SlotName": "FOG_BloodTest_Kit",
                                            "Items": [
                                                {
                                                    "ClassName": "BloodTestKit",
                                                    "Include": "",
                                                    "Chance": 1.0,
                                                    "Quantity": {
                                                        "Min": 0.0,
                                                        "Max": 0.0
                                                    },
                                                    "Health": [],
                                                    "InventoryAttachments": [],
                                                    "InventoryCargo": [],
                                                    "ConstructionPartsBuilt": [],
                                                    "Sets": []
                                                }
                                            ]
                                        }
                                    ],
                                    "InventoryCargo": [],
                                    "ConstructionPartsBuilt": [],
                                    "Sets": []
                                }
                            ]
                        },
                        {
                            "SlotName": "FOG_MRB_dropmag",
                            "Items": [
                                {
                                    "ClassName": "FOG_Pouch_Dump_MC",
                                    "Include": "",
                                    "Chance": 1.0,
                                    "Quantity": {
                                        "Min": 0.0,
                                        "Max": 0.0
                                    },
                                    "Health": [],
                                    "InventoryAttachments": [],
                                    "InventoryCargo": [
                                        {
                                            "ClassName": "BandageDressing",
                                            "Include": "",
                                            "Chance": 1.0,
                                            "Quantity": {
                                                "Min": 1.0,
                                                "Max": 1.0
                                            },
                                            "Health": [],
                                            "InventoryAttachments": [],
                                            "InventoryCargo": [],
                                            "ConstructionPartsBuilt": [],
                                            "Sets": []
                                        },
                                        {
                                            "ClassName": "BandageDressing",
                                            "Include": "",
                                            "Chance": 1.0,
                                            "Quantity": {
                                                "Min": 1.0,
                                                "Max": 1.0
                                            },
                                            "Health": [],
                                            "InventoryAttachments": [],
                                            "InventoryCargo": [],
                                            "ConstructionPartsBuilt": [],
                                            "Sets": []
                                        },
                                        {
                                            "ClassName": "Epinephrine",
                                            "Include": "",
                                            "Chance": 1.0,
                                            "Quantity": {
                                                "Min": 0.0,
                                                "Max": 0.0
                                            },
                                            "Health": [],
                                            "InventoryAttachments": [],
                                            "InventoryCargo": [],
                                            "ConstructionPartsBuilt": [],
                                            "Sets": []
                                        },
                                        {
                                            "ClassName": "TerjePillsIbuprofen",
                                            "Include": "",
                                            "Chance": 1.0,
                                            "Quantity": {
                                                "Min": 1.0,
                                                "Max": 1.0
                                            },
                                            "Health": [],
                                            "InventoryAttachments": [],
                                            "InventoryCargo": [],
                                            "ConstructionPartsBuilt": [],
                                            "Sets": []
                                        }
                                    ],
                                    "ConstructionPartsBuilt": [],
                                    "Sets": []
                                }
                            ]
                        },
                        {
                            "SlotName": "FOG_MRB_esstac",
                            "Items": [
                                {
                                    "ClassName": "FOG_Pouch_Esstac_MC",
                                    "Include": "",
                                    "Chance": 1.0,
                                    "Quantity": {
                                        "Min": 0.0,
                                        "Max": 0.0
                                    },
                                    "Health": [],
                                    "InventoryAttachments": [],
                                    "InventoryCargo": [
                                        {
                                            "ClassName": "DogFoodCan_Opened",
                                            "Include": "",
                                            "Chance": 1.0,
                                            "Quantity": {
                                                "Min": 1.0,
                                                "Max": 1.0
                                            },
                                            "Health": [],
                                            "InventoryAttachments": [],
                                            "InventoryCargo": [],
                                            "ConstructionPartsBuilt": [],
                                            "Sets": []
                                        },
                                        {
                                            "ClassName": "CatFoodCan_Opened",
                                            "Include": "",
                                            "Chance": 1.0,
                                            "Quantity": {
                                                "Min": 1.0,
                                                "Max": 1.0
                                            },
                                            "Health": [],
                                            "InventoryAttachments": [],
                                            "InventoryCargo": [],
                                            "ConstructionPartsBuilt": [],
                                            "Sets": []
                                        }
                                    ],
                                    "ConstructionPartsBuilt": [],
                                    "Sets": []
                                }
                            ]
                        },
                        {
                            "SlotName": "Chemlight",
                            "Items": [
                                {
                                    "ClassName": "Compass",
                                    "Include": "",
                                    "Chance": 1.0,
                                    "Quantity": {
                                        "Min": 0.0,
                                        "Max": 0.0
                                    },
                                    "Health": [],
                                    "InventoryAttachments": [],
                                    "InventoryCargo": [],
                                    "ConstructionPartsBuilt": [],
                                    "Sets": []
                                }
                            ]
                        }
                    ],
                    "InventoryCargo": [],
                    "ConstructionPartsBuilt": [],
                    "Sets": []
                }
            ]
        },
        {
            "SlotName": "Eyewear",
            "Items": [
                {
                    "ClassName": "SkullMask",
                    "Include": "",
                    "Chance": 1.0,
                    "Quantity": {
                        "Min": 0.0,
                        "Max": 0.0
                    },
                    "Health": [],
                    "InventoryAttachments": [],
                    "InventoryCargo": [],
                    "ConstructionPartsBuilt": [],
                    "Sets": []
                }
            ]
        },
        {
            "SlotName": "gloves",
            "Items": [
                {
                    "ClassName": "HandsCover_Improvised",
                    "Include": "",
                    "Chance": 1.0,
                    "Quantity": {
                        "Min": 0.0,
                        "Max": 0.0
                    },
                    "Health": [],
                    "InventoryAttachments": [],
                    "InventoryCargo": [],
                    "ConstructionPartsBuilt": [],
                    "Sets": []
                }
            ]
        },
        {
            "SlotName": "Feet",
            "Items": [
                {
                    "ClassName": "FOG_Operator_Boots_Black",
                    "Include": "",
                    "Chance": 1.0,
                    "Quantity": {
                        "Min": 0.0,
                        "Max": 0.0
                    },
                    "Health": [],
                    "InventoryAttachments": [],
                    "InventoryCargo": [],
                    "ConstructionPartsBuilt": [],
                    "Sets": []
                }
            ]
        },
        {
            "SlotName": "Headgear",
            "Items": [
                {
                    "ClassName": "Shemag_White",
                    "Include": "",
                    "Chance": 1.0,
                    "Quantity": {
                        "Min": 0.0,
                        "Max": 0.0
                    },
                    "Health": [],
                    "InventoryAttachments": [],
                    "InventoryCargo": [],
                    "ConstructionPartsBuilt": [],
                    "Sets": []
                }
            ]
        },
        {
            "SlotName": "Mask",
            "Items": [
                {
                    "ClassName": "BalaclavaMask_Black",
                    "Include": "",
                    "Chance": 1.0,
                    "Quantity": {
                        "Min": 0.0,
                        "Max": 0.0
                    },
                    "Health": [],
                    "InventoryAttachments": [],
                    "InventoryCargo": [],
                    "ConstructionPartsBuilt": [],
                    "Sets": []
                }
            ]
        },
        {
            "SlotName": "Body",
            "Items": [
                {
                    "ClassName": "WinterMilitaryCoat_DarkGrey",
                    "Include": "",
                    "Chance": 1.0,
                    "Quantity": {
                        "Min": 0.0,
                        "Max": 0.0
                    },
                    "Health": [],
                    "InventoryAttachments": [],
                    "InventoryCargo": [
                        {
                            "ClassName": "FlashGrenade",
                            "Include": "",
                            "Chance": 1.0,
                            "Quantity": {
                                "Min": 0.0,
                                "Max": 0.0
                            },
                            "Health": [],
                            "InventoryAttachments": [],
                            "InventoryCargo": [],
                            "ConstructionPartsBuilt": [],
                            "Sets": []
                        },
                        {
                            "ClassName": "Paragon_IFAK_Desert",
                            "Include": "",
                            "Chance": 1.0,
                            "Quantity": {
                                "Min": 1.0,
                                "Max": 1.0
                            },
                            "Health": [],
                            "InventoryAttachments": [],
                            "InventoryCargo": [],
                            "ConstructionPartsBuilt": [],
                            "Sets": []
                        },
                        {
                            "ClassName": "M67Grenade",
                            "Include": "",
                            "Chance": 1.0,
                            "Quantity": {
                                "Min": 0.0,
                                "Max": 0.0
                            },
                            "Health": [],
                            "InventoryAttachments": [],
                            "InventoryCargo": [],
                            "ConstructionPartsBuilt": [],
                            "Sets": []
                        },
                        {
                            "ClassName": "M67Grenade",
                            "Include": "",
                            "Chance": 1.0,
                            "Quantity": {
                                "Min": 0.0,
                                "Max": 0.0
                            },
                            "Health": [],
                            "InventoryAttachments": [],
                            "InventoryCargo": [],
                            "ConstructionPartsBuilt": [],
                            "Sets": []
                        },
                        {
                            "ClassName": "Paragon_IFAK_Desert",
                            "Include": "",
                            "Chance": 1.0,
                            "Quantity": {
                                "Min": 1.0,
                                "Max": 1.0
                            },
                            "Health": [],
                            "InventoryAttachments": [],
                            "InventoryCargo": [],
                            "ConstructionPartsBuilt": [],
                            "Sets": []
                        },
                        {
                            "ClassName": "TF_ChemicalGrenade",
                            "Include": "",
                            "Chance": 1.0,
                            "Quantity": {
                                "Min": 0.0,
                                "Max": 0.0
                            },
                            "Health": [],
                            "InventoryAttachments": [],
                            "InventoryCargo": [],
                            "ConstructionPartsBuilt": [],
                            "Sets": []
                        },
                        {
                            "ClassName": "WaterPouch_Natural",
                            "Include": "",
                            "Chance": 1.0,
                            "Quantity": {
                                "Min": 1.0,
                                "Max": 1.0
                            },
                            "Health": [],
                            "InventoryAttachments": [],
                            "InventoryCargo": [],
                            "ConstructionPartsBuilt": [],
                            "Sets": []
                        }
                    ],
                    "ConstructionPartsBuilt": [],
                    "Sets": []
                }
            ]
        },
        {
            "SlotName": "Vest",
            "Items": [
                {
                    "ClassName": "PlateCarrierVest_Black",
                    "Include": "",
                    "Chance": 1.0,
                    "Quantity": {
                        "Min": 0.0,
                        "Max": 0.0
                    },
                    "Health": [],
                    "InventoryAttachments": [
                        {
                            "SlotName": "Vestpouch",
                            "Items": [
                                {
                                    "ClassName": "PlateCarrierPouches_Black",
                                    "Include": "",
                                    "Chance": 1.0,
                                    "Quantity": {
                                        "Min": 0.0,
                                        "Max": 0.0
                                    },
                                    "Health": [],
                                    "InventoryAttachments": [],
                                    "InventoryCargo": [
                                        {
                                            "ClassName": "MSFC_PP19_Vityaz_Mag_30Rnd",
                                            "Include": "",
                                            "Chance": 1.0,
                                            "Quantity": {
                                                "Min": 1.0,
                                                "Max": 1.0
                                            },
                                            "Health": [],
                                            "InventoryAttachments": [],
                                            "InventoryCargo": [],
                                            "ConstructionPartsBuilt": [],
                                            "Sets": []
                                        },
                                        {
                                            "ClassName": "MSFC_PP19_Vityaz_Mag_30Rnd",
                                            "Include": "",
                                            "Chance": 1.0,
                                            "Quantity": {
                                                "Min": 1.0,
                                                "Max": 1.0
                                            },
                                            "Health": [],
                                            "InventoryAttachments": [],
                                            "InventoryCargo": [],
                                            "ConstructionPartsBuilt": [],
                                            "Sets": []
                                        },
                                        {
                                            "ClassName": "MSFC_PP19_Vityaz_Mag_30Rnd",
                                            "Include": "",
                                            "Chance": 1.0,
                                            "Quantity": {
                                                "Min": 1.0,
                                                "Max": 1.0
                                            },
                                            "Health": [],
                                            "InventoryAttachments": [],
                                            "InventoryCargo": [],
                                            "ConstructionPartsBuilt": [],
                                            "Sets": []
                                        },
                                        {
                                            "ClassName": "Ammo_9x19",
                                            "Include": "",
                                            "Chance": 1.0,
                                            "Quantity": {
                                                "Min": 0.1,
                                                "Max": 0.8
                                            },
                                            "Health": [],
                                            "InventoryAttachments": [],
                                            "InventoryCargo": [],
                                            "ConstructionPartsBuilt": [],
                                            "Sets": []
                                        },
                                        {
                                            "ClassName": "jmc_grenade_z",
                                            "Include": "",
                                            "Chance": 1.0,
                                            "Quantity": {
                                                "Min": 0.0,
                                                "Max": 0.0
                                            },
                                            "Health": [],
                                            "InventoryAttachments": [],
                                            "InventoryCargo": [],
                                            "ConstructionPartsBuilt": [],
                                            "Sets": []
                                        },
                                        {
                                            "ClassName": "RGD5Grenade",
                                            "Include": "",
                                            "Chance": 1.0,
                                            "Quantity": {
                                                "Min": 0.0,
                                                "Max": 0.0
                                            },
                                            "Health": [],
                                            "InventoryAttachments": [],
                                            "InventoryCargo": [],
                                            "ConstructionPartsBuilt": [],
                                            "Sets": []
                                        },
                                        {
                                            "ClassName": "RGD5Grenade",
                                            "Include": "",
                                            "Chance": 1.0,
                                            "Quantity": {
                                                "Min": 0.0,
                                                "Max": 0.0
                                            },
                                            "Health": [],
                                            "InventoryAttachments": [],
                                            "InventoryCargo": [],
                                            "ConstructionPartsBuilt": [],
                                            "Sets": []
                                        }
                                    ],
                                    "ConstructionPartsBuilt": [],
                                    "Sets": []
                                }
                            ]
                        }
                    ],
                    "InventoryCargo": [],
                    "ConstructionPartsBuilt": [],
                    "Sets": []
                }
            ]
        },
        {
            "SlotName": "Legs",
            "Items": [
                {
                    "ClassName": "Jeans_Black",
                    "Include": "",
                    "Chance": 1.0,
                    "Quantity": {
                        "Min": 0.0,
                        "Max": 0.0
                    },
                    "Health": [],
                    "InventoryAttachments": [],
                    "InventoryCargo": [
                        {
                            "ClassName": "TerjeBookStealth1",
                            "Include": "",
                            "Chance": 0.8,
                            "Quantity": {
                                "Min": 0.0,
                                "Max": 0.0
                            },
                            "Health": [],
                            "InventoryAttachments": [],
                            "InventoryCargo": [],
                            "ConstructionPartsBuilt": [],
                            "Sets": []
                        },
                        {
                            "ClassName": "QPK_Ophthalmoscope",
                            "Include": "",
                            "Chance": 0.3,
                            "Quantity": {
                                "Min": 0.0,
                                "Max": 1.0
                            },
                            "Health": [],
                            "InventoryAttachments": [],
                            "InventoryCargo": [],
                            "ConstructionPartsBuilt": [],
                            "Sets": []
                        },
                        {
                            "ClassName": "QPK_SanatoruKey",
                            "Include": "",
                            "Chance": 0.05,
                            "Quantity": {
                                "Min": 0.0,
                                "Max": 0.0
                            },
                            "Health": [],
                            "InventoryAttachments": [],
                            "InventoryCargo": [],
                            "ConstructionPartsBuilt": [],
                            "Sets": []
                        }
                    ],
                    "ConstructionPartsBuilt": [],
                    "Sets": []
                }
            ]
        },
        {
            "SlotName": "Shoulder",
            "Items": [
                {
                    "ClassName": "MSFC_PP19_Vityaz_Black",
                    "Include": "",
                    "Chance": 1.0,
                    "Quantity": {
                        "Min": 1.0,
                        "Max": 1.0
                    },
                    "Health": [],
                    "InventoryAttachments": [
                        {
                            "SlotName": "weaponOptics",
                            "Items": [
                                {
                                    "ClassName": "BO_LeupoldHoloDEVO",
                                    "Include": "",
                                    "Chance": 1.0,
                                    "Quantity": {
                                        "Min": 1.0,
                                        "Max": 1.0
                                    },
                                    "Health": [],
                                    "InventoryAttachments": [],
                                    "InventoryCargo": [],
                                    "ConstructionPartsBuilt": [],
                                    "Sets": []
                                }
                            ]
                        },
                        {
                            "SlotName": "weaponHandguardAK",
                            "Items": [
                                {
                                    "ClassName": "MSFC_AK_Zenitco_Handguard_Black",
                                    "Include": "",
                                    "Chance": 1.0,
                                    "Quantity": {
                                        "Min": 1.0,
                                        "Max": 1.0
                                    },
                                    "Health": [],
                                    "InventoryAttachments": [],
                                    "InventoryCargo": [],
                                    "ConstructionPartsBuilt": [],
                                    "Sets": []
                                }
                            ]
                        },
                        {
                            "SlotName": "pistolMuzzle",
                            "Items": [
                                {
                                    "ClassName": "MSFC_RO_Pistol_Suppressor_Black",
                                    "Include": "",
                                    "Chance": 1.0,
                                    "Quantity": {
                                        "Min": 1.0,
                                        "Max": 1.0
                                    },
                                    "Health": [],
                                    "InventoryAttachments": [],
                                    "InventoryCargo": [],
                                    "ConstructionPartsBuilt": [],
                                    "Sets": []
                                }
                            ]
                        },
                        {
                            "SlotName": "weaponButtstockAK",
                            "Items": [
                                {
                                    "ClassName": "MSFC_AK_Zenitco_Buttstock_Black",
                                    "Include": "",
                                    "Chance": 1.0,
                                    "Quantity": {
                                        "Min": 1.0,
                                        "Max": 1.0
                                    },
                                    "Health": [],
                                    "InventoryAttachments": [],
                                    "InventoryCargo": [],
                                    "ConstructionPartsBuilt": [],
                                    "Sets": []
                                }
                            ]
                        },
                        {
                            "SlotName": "weaponFlashlight",
                            "Items": [
                                {
                                    "ClassName": "SNAFUUniversalLight",
                                    "Include": "",
                                    "Chance": 1.0,
                                    "Quantity": {
                                        "Min": 1.0,
                                        "Max": 1.0
                                    },
                                    "Health": [],
                                    "InventoryAttachments": [
                                        {
                                            "SlotName": "BatteryD",
                                            "Items": [
                                                {
                                                    "ClassName": "Battery9V",
                                                    "Include": "",
                                                    "Chance": 1.0,
                                                    "Quantity": {
                                                        "Min": 1.0,
                                                        "Max": 1.0
                                                    },
                                                    "Health": [],
                                                    "InventoryAttachments": [],
                                                    "InventoryCargo": [],
                                                    "ConstructionPartsBuilt": [],
                                                    "Sets": []
                                                }
                                            ]
                                        }
                                    ],
                                    "InventoryCargo": [],
                                    "ConstructionPartsBuilt": [],
                                    "Sets": []
                                }
                            ]
                        },
                        {
                            "SlotName": "Magazine",
                            "Items": [
                                {
                                    "ClassName": "MSFC_PP19_Vityaz_Mag_30Rnd",
                                    "Include": "",
                                    "Chance": 1.0,
                                    "Quantity": {
                                        "Min": 1.0,
                                        "Max": 1.0
                                    },
                                    "Health": [],
                                    "InventoryAttachments": [],
                                    "InventoryCargo": [],
                                    "ConstructionPartsBuilt": [],
                                    "Sets": []
                                }
                            ]
                        }
                    ],
                    "InventoryCargo": [],
                    "ConstructionPartsBuilt": [],
                    "Sets": []
                }
            ]
        },
        {
            "SlotName": "Back",
            "Items": [
                {
                    "ClassName": "SlingBag_Gray",
                    "Include": "",
                    "Chance": 1.0,
                    "Quantity": {
                        "Min": 0.0,
                        "Max": 0.0
                    },
                    "Health": [],
                    "InventoryAttachments": [
                        {
                            "SlotName": "WalkieTalkie",
                            "Items": [
                                {
                                    "ClassName": "Compass",
                                    "Include": "",
                                    "Chance": 1.0,
                                    "Quantity": {
                                        "Min": 0.0,
                                        "Max": 0.0
                                    },
                                    "Health": [],
                                    "InventoryAttachments": [],
                                    "InventoryCargo": [],
                                    "ConstructionPartsBuilt": [],
                                    "Sets": []
                                }
                            ]
                        },
                        {
                            "SlotName": "Backpack_1",
                            "Items": [
                                {
                                    "ClassName": "Crowbar",
                                    "Include": "",
                                    "Chance": 1.0,
                                    "Quantity": {
                                        "Min": 1.0,
                                        "Max": 1.0
                                    },
                                    "Health": [],
                                    "InventoryAttachments": [],
                                    "InventoryCargo": [],
                                    "ConstructionPartsBuilt": [],
                                    "Sets": []
                                }
                            ]
                        }
                    ],
                    "InventoryCargo": [],
                    "ConstructionPartsBuilt": [],
                    "Sets": []
                }
            ]
        }
    ],
    "InventoryCargo": [],
    "ConstructionPartsBuilt": [],
    "Sets": []
}