{
    "ClassName": "",
    "Include": "",
    "Chance": 1.0,
    "Quantity": {
        "Min": 0.0,
        "Max": 0.0
    },
    "Health": [],
    "InventoryAttachments": [
        {
            "SlotName": "Body",
            "Items": [
                {
                    "ClassName": "FOG_Hooded_Parka_Black",
                    "Include": "",
                    "Chance": 1.0,
                    "Quantity": {
                        "Min": 0.0,
                        "Max": 0.0
                    },
                    "Health": [
                        {
                            "Min": 0.7,
                            "Max": 1.0,
                            "Zone": ""
                        }
                    ],
                    "InventoryAttachments": [],
                    "InventoryCargo": [],
                    "ConstructionPartsBuilt": [],
                    "Sets": []
                }
            ]
        },
        {
            "SlotName": "Legs",
            "Items": [
                {
                    "ClassName": "CargoPants_Black",
                    "Include": "",
                    "Chance": 1.0,
                    "Quantity": {
                        "Min": 0.0,
                        "Max": 0.0
                    },
                    "Health": [
                        {
                            "Min": 0.7,
                            "Max": 1.0,
                            "Zone": ""
                        }
                    ],
                    "InventoryAttachments": [],
                    "InventoryCargo": [],
                    "ConstructionPartsBuilt": [],
                    "Sets": []
                }
            ]
        },
        {
            "SlotName": "Feet",
            "Items": [
                {
                    "ClassName": "SK8_Sneakers_Black",
                    "Include": "",
                    "Chance": 1.0,
                    "Quantity": {
                        "Min": 0.0,
                        "Max": 0.0
                    },
                    "Health": [
                        {
                            "Min": 0.7,
                            "Max": 1.0,
                            "Zone": ""
                        }
                    ],
                    "InventoryAttachments": [],
                    "InventoryCargo": [],
                    "ConstructionPartsBuilt": [],
                    "Sets": []
                }
            ]
        },
        {
            "SlotName": "Headgear",
            "Items": [
                {
                    "ClassName": "BeanieHat_Beige",
                    "Include": "",
                    "Chance": 1.0,
                    "Quantity": {
                        "Min": 0.0,
                        "Max": 0.0
                    },
                    "Health": [
                        {
                            "Min": 0.699999988079071,
                            "Max": 1.0,
                            "Zone": ""
                        }
                    ],
                    "InventoryAttachments": [],
                    "InventoryCargo": [],
                    "ConstructionPartsBuilt": [],
                    "Sets": []
                }
            ]
        },
        {
            "SlotName": "Gloves",
            "Items": [
                {
                    "ClassName": "FOG_PIGFDT_Gloves_CB",
                    "Include": "",
                    "Chance": 1.0,
                    "Quantity": {
                        "Min": 0.0,
                        "Max": 0.0
                    },
                    "Health": [
                        {
                            "Min": 0.699999988079071,
                            "Max": 1.0,
                            "Zone": ""
                        }
                    ],
                    "InventoryAttachments": [],
                    "InventoryCargo": [],
                    "ConstructionPartsBuilt": [],
                    "Sets": []
                }
            ]
        },
        {
            "SlotName": "Back",
            "Items": [
                {
                    "ClassName": "FOG_Bag_CommsBag_Tan",
                    "Include": "",
                    "Chance": 0.03,
                    "Quantity": {
                        "Min": 0.0,
                        "Max": 0.0
                    },
                    "Health": [
                        {
                            "Min": 0.699999988079071,
                            "Max": 1.0,
                            "Zone": ""
                        }
                    ],
                    "InventoryAttachments": [],
                    "InventoryCargo": [],
                    "ConstructionPartsBuilt": [],
                    "Sets": []
                }
            ]
        },
        {
            "SlotName": "Eyes",
            "Items": [
                {
                    "ClassName": "Gekoseasteregg",
                    "Include": "",
                    "Chance": 1.0,
                    "Quantity": {
                        "Min": 0.0,
                        "Max": 0.0
                    },
                    "Health": [
                        {
                            "Min": 0.699999988079071,
                            "Max": 1.0,
                            "Zone": ""
                        }
                    ],
                    "InventoryAttachments": [],
                    "InventoryCargo": [],
                    "ConstructionPartsBuilt": [],
                    "Sets": []
                }
            ]
        },
        {
            "SlotName": "MASK",
            "Items": [
                {
                    "ClassName": "Scarf_Brown",
                    "Include": "",
                    "Chance": 1.0,
                    "Quantity": {
                        "Min": 0.0,
                        "Max": 0.0
                    },
                    "Health": [
                        {
                            "Min": 0.699999988079071,
                            "Max": 1.0,
                            "Zone": ""
                        }
                    ],
                    "InventoryAttachments": [],
                    "InventoryCargo": [],
                    "ConstructionPartsBuilt": [],
                    "Sets": []
                }
            ]
        },
        {
            "SlotName": "Vest",
            "Items": []
        },
        {
            "SlotName": "Hips",
            "Items": [
                {
                    "ClassName": "FOG_Belt_TacticalFanny_CB",
                    "Include": "",
                    "Chance": 1.0,
                    "Quantity": {
                        "Min": 0.0,
                        "Max": 0.0
                    },
                    "Health": [
                        {
                            "Min": 0.699999988079071,
                            "Max": 1.0,
                            "Zone": ""
                        }
                    ],
                    "InventoryAttachments": [],
                    "InventoryCargo": [],
                    "ConstructionPartsBuilt": [],
                    "Sets": []
                }
            ]
        },
        {
            "SlotName": "Melee",
            "Items": []
        }
    ],
    "InventoryCargo": [],
    "ConstructionPartsBuilt": [],
    "Sets": [
        {
            "ClassName": "WEAPON",
            "Chance": 1.0,
            "Quantity": {
                "Min": 0.0,
                "Max": 0.0
            },
            "Health": [],
            "InventoryAttachments": [
                {
                    "SlotName": "Hands",
                    "Items": [
                        {
                            "ClassName": "GPSReceiver",
                            "Chance": 1.0,
                            "Quantity": {
                                "Min": 0.0,
                                "Max": 0.0
                            },
                            "Health": [
                                {
                                    "Min": 1.0,
                                    "Max": 1.0,
                                    "Zone": ""
                                }
                            ],
                            "InventoryAttachments": [],
                            "InventoryCargo": [],
                            "ConstructionPartsBuilt": [],
                            "Sets": []
                        }
                    ]
                }
            ],
            "InventoryCargo": [],
            "ConstructionPartsBuilt": [],
            "Sets": []
        }
    ]
}